<PAMDataset>
  <Metadata domain="ESRI">
    <MDI key="PyramidResamplingType">NEAREST</MDI>
  </Metadata>
  <PAMRasterBand band="1">
    <Metadata>
      <MDI key="STATISTICS_MINIMUM">0</MDI>
      <MDI key="STATISTICS_MAXIMUM">255</MDI>
      <MDI key="STATISTICS_MEAN">54.888666503978</MDI>
      <MDI key="STATISTICS_STDDEV">51.127406703637</MDI>
    </Metadata>
  </PAMRasterBand>
  <PAMRasterBand band="2">
    <Metadata>
      <MDI key="STATISTICS_MINIMUM">0</MDI>
      <MDI key="STATISTICS_MAXIMUM">255</MDI>
      <MDI key="STATISTICS_MEAN">64.9371582226</MDI>
      <MDI key="STATISTICS_STDDEV">53.703062627537</MDI>
    </Metadata>
  </PAMRasterBand>
  <PAMRasterBand band="3">
    <Metadata>
      <MDI key="STATISTICS_MINIMUM">0</MDI>
      <MDI key="STATISTICS_MAXIMUM">255</MDI>
      <MDI key="STATISTICS_MEAN">51.683201214392</MDI>
      <MDI key="STATISTICS_STDDEV">45.519553571382</MDI>
    </Metadata>
  </PAMRasterBand>
</PAMDataset>
